aioeos/__init__.py
aioeos/account.py
aioeos/contracts/__init__.py
aioeos/contracts/eosio.py
aioeos/contracts/eosio_token.py
aioeos/exceptions.py
aioeos/keys.py
aioeos/rpc.py
aioeos/serializer.py
aioeos/types/__init__.py
aioeos/types/abi.py
aioeos/types/authority.py
aioeos/types/transaction.py
aioeos-1.0.2.dist-info/LICENSE
aioeos-1.0.2.dist-info/WHEEL
aioeos-1.0.2.dist-info/METADATA
aioeos-1.0.2.dist-info/RECORD
