Metadata-Version: 2.1
Name: aioeos
Version: 1.0.2
Summary: Async library for interacting with EOS.io blockchain
Home-page: https://ulam.io/
License: MIT
Keywords: blockchain,eos,async,eosio,cryptocurrency
Author: Maciej Janiszewski
Author-email: maciej@ulam.io
Requires-Python: >=3.7,<4.0
Classifier: License :: OSI Approved :: MIT License
Classifier: Programming Language :: Python :: 3
Classifier: Programming Language :: Python :: 3.7
Classifier: Programming Language :: Python :: 3.8
Requires-Dist: aiohttp (>=3.3.1,<4.0.0)
Requires-Dist: base58 (==2.0.0)
Requires-Dist: ecdsa (>=0.15,<0.16)
Project-URL: Documentation, https://aioeos.readthedocs.io/en/latest/
Project-URL: Repository, https://github.com/ulamlabs/aioeos
